{
  "minecraft:recipes/decorations/light_blue_bed_from_white_bed": {
    "criteria": {
      "has_bed": "2022-08-07 16:29:42 +0000"
    },
    "done": true
  },
  "minecraft:recipes/misc/iron_nugget_from_blasting": {
    "criteria": {
      "has_iron_boots": "2022-08-07 16:21:50 +0000"
    },
    "done": true
  },
  "minecraft:recipes/building_blocks/raw_copper_block": {
    "criteria": {
      "has_raw_copper": "2022-08-07 16:30:30 +0000"
    },
    "done": true
  },
  "minecraft:nether/obtain_crying_obsidian": {
    "criteria": {
      "crying_obsidian": "2022-08-07 16:22:33 +0000"
    },
    "done": true
  },
  "minecraft:recipes/decorations/magenta_bed_from_white_bed": {
    "criteria": {
      "has_bed": "2022-08-07 16:29:42 +0000"
    },
    "done": true
  },
  "minecraft:recipes/misc/paper": {
    "criteria": {
      "has_reeds": "2022-08-07 16:23:56 +0000"
    },
    "done": true
  },
  "minecraft:end/root": {
    "criteria": {
      "entered_end": "2022-08-07 16:29:03 +0000"
    },
    "done": true
  },
  "minecraft:recipes/decorations/orange_bed_from_white_bed": {
    "criteria": {
      "has_bed": "2022-08-07 16:29:42 +0000"
    },
    "done": true
  },
  "minecraft:story/obtain_armor": {
    "criteria": {
      "iron_boots": "2022-08-07 16:21:50 +0000"
    },
    "done": true
  },
  "minecraft:recipes/combat/diamond_chestplate": {
    "criteria": {
      "has_diamond": "2022-08-07 16:23:05 +0000"
    },
    "done": true
  },
  "minecraft:recipes/tools/diamond_axe": {
    "criteria": {
      "has_diamond": "2022-08-07 16:23:05 +0000"
    },
    "done": true
  },
  "minecraft:nether/root": {
    "criteria": {
      "entered_nether": "2022-08-07 16:27:17 +0000"
    },
    "done": true
  },
  "minecraft:adventure/adventuring_time": {
    "criteria": {
      "minecraft:beach": "2022-08-07 16:22:08 +0000",
      "minecraft:river": "2022-08-07 16:24:11 +0000",
      "minecraft:stony_shore": "2022-08-07 16:24:27 +0000",
      "minecraft:lush_caves": "2022-08-07 16:28:57 +0000",
      "minecraft:ocean": "2022-08-07 16:25:41 +0000",
      "minecraft:flower_forest": "2022-08-07 16:20:38 +0000"
    },
    "done": false
  },
  "minecraft:recipes/combat/diamond_leggings": {
    "criteria": {
      "has_diamond": "2022-08-07 16:23:05 +0000"
    },
    "done": true
  },
  "minecraft:recipes/decorations/purple_bed_from_white_bed": {
    "criteria": {
      "has_bed": "2022-08-07 16:29:42 +0000"
    },
    "done": true
  },
  "minecraft:recipes/food/bread": {
    "criteria": {
      "has_wheat": "2022-08-07 16:24:27 +0000"
    },
    "done": true
  },
  "minecraft:recipes/misc/copper_ingot_from_smelting_raw_copper": {
    "criteria": {
      "has_raw_copper": "2022-08-07 16:30:30 +0000"
    },
    "done": true
  },
  "minecraft:story/shiny_gear": {
    "criteria": {
      "diamond_leggings": "2022-08-07 16:21:52 +0000"
    },
    "done": true
  },
  "minecraft:recipes/transportation/birch_boat": {
    "criteria": {
      "in_water": "2022-08-07 16:24:06 +0000"
    },
    "done": true
  },
  "minecraft:recipes/decorations/black_bed_from_white_bed": {
    "criteria": {
      "has_bed": "2022-08-07 16:29:42 +0000"
    },
    "done": true
  },
  "minecraft:recipes/transportation/mangrove_boat": {
    "criteria": {
      "in_water": "2022-08-07 16:24:06 +0000"
    },
    "done": true
  },
  "minecraft:recipes/transportation/acacia_boat": {
    "criteria": {
      "in_water": "2022-08-07 16:24:06 +0000"
    },
    "done": true
  },
  "minecraft:recipes/misc/copper_ingot_from_blasting_raw_copper": {
    "criteria": {
      "has_raw_copper": "2022-08-07 16:30:30 +0000"
    },
    "done": true
  },
  "minecraft:recipes/combat/diamond_sword": {
    "criteria": {
      "has_diamond": "2022-08-07 16:23:05 +0000"
    },
    "done": true
  },
  "minecraft:recipes/decorations/cyan_bed_from_white_bed": {
    "criteria": {
      "has_bed": "2022-08-07 16:29:42 +0000"
    },
    "done": true
  },
  "minecraft:recipes/combat/arrow": {
    "criteria": {
      "has_flint": "2022-08-07 16:30:21 +0000"
    },
    "done": true
  },
  "minecraft:adventure/root": {
    "criteria": {
      "killed_by_something": "2022-08-07 16:23:21 +0000"
    },
    "done": true
  },
  "minecraft:husbandry/plant_seed": {
    "criteria": {
      "wheat": "2022-08-07 16:24:37 +0000"
    },
    "done": true
  },
  "minecraft:recipes/transportation/jungle_boat": {
    "criteria": {
      "in_water": "2022-08-07 16:24:06 +0000"
    },
    "done": true
  },
  "minecraft:recipes/decorations/jukebox": {
    "criteria": {
      "has_diamond": "2022-08-07 16:23:05 +0000"
    },
    "done": true
  },
  "minecraft:recipes/transportation/spruce_boat": {
    "criteria": {
      "in_water": "2022-08-07 16:24:06 +0000"
    },
    "done": true
  },
  "minecraft:recipes/decorations/gray_bed_from_white_bed": {
    "criteria": {
      "has_bed": "2022-08-07 16:29:42 +0000"
    },
    "done": true
  },
  "minecraft:recipes/tools/flint_and_steel": {
    "criteria": {
      "has_flint": "2022-08-07 16:30:21 +0000"
    },
    "done": true
  },
  "minecraft:recipes/redstone/dispenser": {
    "criteria": {
      "has_bow": "2022-08-07 16:25:52 +0000"
    },
    "done": true
  },
  "minecraft:recipes/decorations/lime_bed_from_white_bed": {
    "criteria": {
      "has_bed": "2022-08-07 16:29:42 +0000"
    },
    "done": true
  },
  "minecraft:recipes/building_blocks/diamond_block": {
    "criteria": {
      "has_diamond": "2022-08-07 16:23:05 +0000"
    },
    "done": true
  },
  "minecraft:recipes/transportation/dark_oak_boat": {
    "criteria": {
      "in_water": "2022-08-07 16:24:06 +0000"
    },
    "done": true
  },
  "minecraft:recipes/tools/diamond_pickaxe": {
    "criteria": {
      "has_diamond": "2022-08-07 16:23:05 +0000"
    },
    "done": true
  },
  "minecraft:recipes/tools/diamond_hoe": {
    "criteria": {
      "has_diamond": "2022-08-07 16:23:05 +0000"
    },
    "done": true
  },
  "minecraft:recipes/food/dried_kelp": {
    "criteria": {
      "has_dried_kelp_block": "2022-08-07 16:27:04 +0000"
    },
    "done": true
  },
  "minecraft:recipes/food/cake": {
    "criteria": {
      "has_egg": "2022-08-07 16:22:43 +0000"
    },
    "done": true
  },
  "minecraft:recipes/tools/diamond_shovel": {
    "criteria": {
      "has_diamond": "2022-08-07 16:23:05 +0000"
    },
    "done": true
  },
  "minecraft:story/enter_the_nether": {
    "criteria": {
      "entered_nether": "2022-08-07 16:27:17 +0000"
    },
    "done": true
  },
  "minecraft:recipes/misc/sugar_from_sugar_cane": {
    "criteria": {
      "has_sugar_cane": "2022-08-07 16:23:56 +0000"
    },
    "done": true
  },
  "minecraft:story/enter_the_end": {
    "criteria": {
      "entered_end": "2022-08-07 16:29:03 +0000"
    },
    "done": true
  },
  "minecraft:recipes/decorations/green_bed_from_white_bed": {
    "criteria": {
      "has_bed": "2022-08-07 16:29:42 +0000"
    },
    "done": true
  },
  "minecraft:recipes/decorations/brown_bed_from_white_bed": {
    "criteria": {
      "has_bed": "2022-08-07 16:29:42 +0000"
    },
    "done": true
  },
  "minecraft:recipes/decorations/fletching_table": {
    "criteria": {
      "has_flint": "2022-08-07 16:30:21 +0000"
    },
    "done": true
  },
  "minecraft:recipes/decorations/respawn_anchor": {
    "criteria": {
      "has_obsidian": "2022-08-07 16:22:33 +0000"
    },
    "done": true
  },
  "minecraft:recipes/decorations/pink_bed_from_white_bed": {
    "criteria": {
      "has_bed": "2022-08-07 16:29:42 +0000"
    },
    "done": true
  },
  "minecraft:recipes/misc/iron_nugget_from_smelting": {
    "criteria": {
      "has_iron_boots": "2022-08-07 16:21:50 +0000"
    },
    "done": true
  },
  "minecraft:nether/explore_nether": {
    "criteria": {
      "minecraft:nether_wastes": "2022-08-07 16:27:50 +0000",
      "minecraft:basalt_deltas": "2022-08-07 16:27:18 +0000"
    },
    "done": false
  },
  "minecraft:recipes/decorations/yellow_bed_from_white_bed": {
    "criteria": {
      "has_bed": "2022-08-07 16:29:42 +0000"
    },
    "done": true
  },
  "minecraft:recipes/misc/diamond": {
    "criteria": {
      "has_diamond_block": "2022-08-07 16:23:04 +0000"
    },
    "done": true
  },
  "minecraft:recipes/combat/diamond_boots": {
    "criteria": {
      "has_diamond": "2022-08-07 16:23:05 +0000"
    },
    "done": true
  },
  "minecraft:story/mine_diamond": {
    "criteria": {
      "diamond": "2022-08-07 16:23:05 +0000"
    },
    "done": true
  },
  "minecraft:recipes/combat/diamond_helmet": {
    "criteria": {
      "has_diamond": "2022-08-07 16:23:05 +0000"
    },
    "done": true
  },
  "minecraft:recipes/decorations/red_bed_from_white_bed": {
    "criteria": {
      "has_bed": "2022-08-07 16:29:42 +0000"
    },
    "done": true
  },
  "minecraft:recipes/transportation/oak_boat": {
    "criteria": {
      "in_water": "2022-08-07 16:24:06 +0000"
    },
    "done": true
  },
  "minecraft:story/follow_ender_eye": {
    "criteria": {
      "in_stronghold": "2022-08-07 16:28:57 +0000"
    },
    "done": true
  },
  "minecraft:recipes/decorations/blue_bed_from_white_bed": {
    "criteria": {
      "has_bed": "2022-08-07 16:29:42 +0000"
    },
    "done": true
  },
  "minecraft:recipes/decorations/light_gray_bed_from_white_bed": {
    "criteria": {
      "has_bed": "2022-08-07 16:29:42 +0000"
    },
    "done": true
  },
  "minecraft:recipes/building_blocks/hay_block": {
    "criteria": {
      "has_wheat": "2022-08-07 16:24:27 +0000"
    },
    "done": true
  },
  "DataVersion": 3105
}